[{"score":9,"score_max":11,"score_min":6,"flag":1,"level":1,"start_time":1674824340000,"end_time":1674824399000},{"score":20,"score_max":34,"score_min":6,"flag":1,"level":1,"start_time":1674824280000,"end_time":1674824339000},{"score":10,"score_max":34,"score_min":2,"flag":1,"level":1,"start_time":1674824220000,"end_time":1674824279000},{"score":2,"score_max":4,"score_min":1,"flag":1,"level":1,"start_time":1674824160000,"end_time":1674824219000},{"score":5,"score_max":6,"score_min":4,"flag":1,"level":1,"start_time":1674824100000,"end_time":1674824159000},{"score":5,"score_max":6,"score_min":4,"flag":1,"level":1,"start_time":1674824040000,"end_time":1674824099000},{"score":3,"score_max":8,"score_min":3,"flag":1,"level":1,"start_time":1674823980000,"end_time":1674824039000},{"score":16,"score_max":23,"score_min":9,"flag":1,"level":1,"start_time":1674823920000,"end_time":1674823979000},{"score":2,"score_max":2,"score_min":2,"flag":1,"level":1,"start_time":1674823860000,"end_time":1674823919000},{"score":3,"score_max":7,"score_min":2,"flag":1,"level":1,"start_time":1674823800000,"end_time":1674823859000},{"score":5,"score_max":7,"score_min":3,"flag":1,"level":1,"start_time":1674823740000,"end_time":1674823799000},{"score":2,"score_max":3,"score_min":0,"flag":1,"level":1,"start_time":1674823680000,"end_time":1674823739000},{"score":0,"score_max":0,"score_min":0,"flag":1,"level":1,"start_time":1674823440000,"end_time":1674823499000},{"score":61,"score_max":78,"score_min":48,"flag":1,"level":1,"start_time":1674823380000,"end_time":1674823439000},{"score":21,"score_max":46,"score_min":9,"flag":1,"level":1,"start_time":1674823320000,"end_time":1674823379000},{"score":4,"score_max":9,"score_min":1,"flag":1,"level":1,"start_time":1674823200000,"end_time":1674823259000}]