[{"heart_rate":90,"heart_rate_max":96,"heart_rate_min":84,"start_time":1675303140000,"end_time":1675303199000},{"heart_rate":91,"heart_rate_max":95,"heart_rate_min":84,"start_time":1675303080000,"end_time":1675303139000},{"heart_rate":88,"heart_rate_max":94,"heart_rate_min":85,"start_time":1675303020000,"end_time":1675303079000},{"heart_rate":90,"heart_rate_max":93,"heart_rate_min":89,"start_time":1675302960000,"end_time":1675303019000},{"heart_rate":88,"heart_rate_max":92,"heart_rate_min":85,"start_time":1675302900000,"end_time":1675302959000},{"heart_rate":88,"heart_rate_max":93,"heart_rate_min":84,"start_time":1675302840000,"end_time":1675302899000},{"heart_rate":87,"heart_rate_max":90,"heart_rate_min":83,"start_time":1675302780000,"end_time":1675302839000},{"heart_rate":88,"heart_rate_max":95,"heart_rate_min":85,"start_time":1675302720000,"end_time":1675302779000},{"heart_rate":89,"heart_rate_max":96,"heart_rate_min":84,"start_time":1675302660000,"end_time":1675302719000},{"heart_rate":89,"heart_rate_max":94,"heart_rate_min":86,"start_time":1675302600000,"end_time":1675302659000},{"heart_rate":89,"heart_rate_max":92,"heart_rate_min":86,"start_time":1675302540000,"end_time":1675302599000},{"heart_rate":88,"heart_rate_max":93,"heart_rate_min":86,"start_time":1675302480000,"end_time":1675302539000},{"heart_rate":94,"heart_rate_max":97,"heart_rate_min":93,"start_time":1675302420000,"end_time":1675302479000},{"heart_rate":99,"heart_rate_max":104,"heart_rate_min":96,"start_time":1675302360000,"end_time":1675302419000},{"heart_rate":98,"heart_rate_max":98,"heart_rate_min":98,"start_time":1675302300000,"end_time":1675302359000},{"heart_rate":94,"heart_rate_max":97,"heart_rate_min":91,"start_time":1675301940000,"end_time":1675301999000},{"heart_rate":94,"heart_rate_max":99,"heart_rate_min":91,"start_time":1675301880000,"end_time":1675301939000},{"heart_rate":95,"heart_rate_max":97,"heart_rate_min":91,"start_time":1675301820000,"end_time":1675301879000},{"heart_rate":80,"heart_rate_max":96,"heart_rate_min":71,"start_time":1675301760000,"end_time":1675301819000},{"heart_rate":84,"heart_rate_max":91,"heart_rate_min":77,"start_time":1675301700000,"end_time":1675301759000},{"heart_rate":97,"heart_rate_max":101,"heart_rate_min":96,"start_time":1675301580000,"end_time":1675301639000},{"heart_rate":94,"heart_rate_max":97,"heart_rate_min":92,"start_time":1675301520000,"end_time":1675301579000},{"heart_rate":98,"heart_rate_max":100,"heart_rate_min":98,"start_time":1675301400000,"end_time":1675301459000},{"heart_rate":90,"heart_rate_max":96,"heart_rate_min":86,"start_time":1675301160000,"end_time":1675301219000},{"heart_rate":84,"heart_rate_max":87,"heart_rate_min":79,"start_time":1675301100000,"end_time":1675301159000},{"heart_rate":93,"heart_rate_max":98,"heart_rate_min":90,"start_time":1675301040000,"end_time":1675301099000},{"heart_rate":93,"heart_rate_max":99,"heart_rate_min":88,"start_time":1675300980000,"end_time":1675301039000},{"heart_rate":97,"heart_rate_max":98,"heart_rate_min":96,"start_time":1675300920000,"end_time":1675300979000},{"heart_rate":90,"heart_rate_max":92,"heart_rate_min":88,"start_time":1675300860000,"end_time":1675300919000},{"heart_rate":89,"heart_rate_max":94,"heart_rate_min":83,"start_time":1675300800000,"end_time":1675300859000},{"heart_rate":84,"heart_rate_max":90,"heart_rate_min":82,"start_time":1675300740000,"end_time":1675300799000},{"heart_rate":94,"heart_rate_max":96,"heart_rate_min":94,"start_time":1675300680000,"end_time":1675300739000},{"heart_rate":95,"heart_rate_max":97,"heart_rate_min":93,"start_time":1675300620000,"end_time":1675300679000},{"heart_rate":96,"heart_rate_max":98,"heart_rate_min":95,"start_time":1675300560000,"end_time":1675300619000},{"heart_rate":98,"heart_rate_max":99,"heart_rate_min":98,"start_time":1675300500000,"end_time":1675300559000},{"heart_rate":111,"heart_rate_max":116,"heart_rate_min":106,"start_time":1675300260000,"end_time":1675300319000},{"heart_rate":103,"heart_rate_max":106,"heart_rate_min":100,"start_time":1675300200000,"end_time":1675300259000},{"heart_rate":101,"heart_rate_max":104,"heart_rate_min":98,"start_time":1675300140000,"end_time":1675300199000},{"heart_rate":92,"heart_rate_max":100,"heart_rate_min":90,"start_time":1675300080000,"end_time":1675300139000},{"heart_rate":101,"heart_rate_max":102,"heart_rate_min":100,"start_time":1675300020000,"end_time":1675300079000},{"heart_rate":90,"heart_rate_max":92,"heart_rate_min":89,"start_time":1675299960000,"end_time":1675300019000},{"heart_rate":85,"heart_rate_max":89,"heart_rate_min":83,"start_time":1675299900000,"end_time":1675299959000},{"heart_rate":94,"heart_rate_max":95,"heart_rate_min":93,"start_time":1675299840000,"end_time":1675299899000},{"heart_rate":86,"heart_rate_max":91,"heart_rate_min":82,"start_time":1675299780000,"end_time":1675299839000},{"heart_rate":88,"heart_rate_max":94,"heart_rate_min":87,"start_time":1675299720000,"end_time":1675299779000},{"heart_rate":95,"heart_rate_max":95,"heart_rate_min":95,"start_time":1675299660000,"end_time":1675299719000},{"heart_rate":97,"heart_rate_max":98,"heart_rate_min":97,"start_time":1675299600000,"end_time":1675299659000}]