[{"score":20,"score_max":42,"score_min":14,"flag":1,"level":1,"start_time":1675569540000,"end_time":1675569599000},{"score":37,"score_max":47,"score_min":32,"flag":1,"level":1,"start_time":1675569480000,"end_time":1675569539000},{"score":2,"score_max":3,"score_min":2,"flag":1,"level":1,"start_time":1675569420000,"end_time":1675569479000},{"score":2,"score_max":5,"score_min":1,"flag":1,"level":1,"start_time":1675569300000,"end_time":1675569359000},{"score":8,"score_max":8,"score_min":8,"flag":1,"level":1,"start_time":1675569240000,"end_time":1675569299000},{"score":6,"score_max":10,"score_min":5,"flag":1,"level":1,"start_time":1675569180000,"end_time":1675569239000},{"score":5,"score_max":11,"score_min":4,"flag":1,"level":1,"start_time":1675569120000,"end_time":1675569179000},{"score":8,"score_max":12,"score_min":4,"flag":1,"level":1,"start_time":1675569060000,"end_time":1675569119000},{"score":6,"score_max":10,"score_min":4,"flag":1,"level":1,"start_time":1675569000000,"end_time":1675569059000},{"score":3,"score_max":4,"score_min":3,"flag":1,"level":1,"start_time":1675568940000,"end_time":1675568999000},{"score":18,"score_max":47,"score_min":3,"flag":1,"level":1,"start_time":1675568880000,"end_time":1675568939000},{"score":11,"score_max":39,"score_min":2,"flag":1,"level":1,"start_time":1675568820000,"end_time":1675568879000},{"score":2,"score_max":2,"score_min":2,"flag":1,"level":1,"start_time":1675568760000,"end_time":1675568819000},{"score":2,"score_max":3,"score_min":2,"flag":1,"level":1,"start_time":1675568700000,"end_time":1675568759000},{"score":3,"score_max":3,"score_min":3,"flag":1,"level":1,"start_time":1675568580000,"end_time":1675568639000},{"score":0,"score_max":0,"score_min":0,"flag":1,"level":1,"start_time":1675568520000,"end_time":1675568579000},{"score":1,"score_max":3,"score_min":0,"flag":1,"level":1,"start_time":1675568400000,"end_time":1675568459000},{"score":1,"score_max":1,"score_min":1,"flag":1,"level":1,"start_time":1675568340000,"end_time":1675568399000},{"score":1,"score_max":2,"score_min":1,"flag":1,"level":1,"start_time":1675568280000,"end_time":1675568339000},{"score":4,"score_max":6,"score_min":2,"flag":1,"level":1,"start_time":1675568220000,"end_time":1675568279000},{"score":1,"score_max":4,"score_min":1,"flag":1,"level":1,"start_time":1675568160000,"end_time":1675568219000},{"score":6,"score_max":8,"score_min":4,"flag":1,"level":1,"start_time":1675568100000,"end_time":1675568159000},{"score":5,"score_max":6,"score_min":4,"flag":1,"level":1,"start_time":1675568040000,"end_time":1675568099000},{"score":5,"score_max":6,"score_min":5,"flag":1,"level":1,"start_time":1675567980000,"end_time":1675568039000},{"score":6,"score_max":8,"score_min":6,"flag":1,"level":1,"start_time":1675567920000,"end_time":1675567979000},{"score":27,"score_max":68,"score_min":7,"flag":1,"level":1,"start_time":1675567860000,"end_time":1675567919000},{"score":47,"score_max":76,"score_min":32,"flag":1,"level":1,"start_time":1675567800000,"end_time":1675567859000},{"score":33,"score_max":39,"score_min":28,"flag":1,"level":1,"start_time":1675567740000,"end_time":1675567799000},{"score":29,"score_max":38,"score_min":19,"flag":1,"level":1,"start_time":1675567680000,"end_time":1675567739000},{"score":15,"score_max":22,"score_min":13,"flag":1,"level":1,"start_time":1675567620000,"end_time":1675567679000},{"score":34,"score_max":42,"score_min":23,"flag":1,"level":1,"start_time":1675567560000,"end_time":1675567619000},{"score":25,"score_max":31,"score_min":22,"flag":1,"level":1,"start_time":1675567500000,"end_time":1675567559000},{"score":23,"score_max":33,"score_min":16,"flag":1,"level":1,"start_time":1675567440000,"end_time":1675567499000},{"score":12,"score_max":17,"score_min":4,"flag":1,"level":1,"start_time":1675567380000,"end_time":1675567439000},{"score":1,"score_max":4,"score_min":1,"flag":1,"level":1,"start_time":1675567320000,"end_time":1675567379000},{"score":2,"score_max":3,"score_min":2,"flag":1,"level":1,"start_time":1675567260000,"end_time":1675567319000},{"score":2,"score_max":3,"score_min":2,"flag":1,"level":1,"start_time":1675567200000,"end_time":1675567259000},{"score":0,"score_max":2,"score_min":0,"flag":1,"level":1,"start_time":1675567140000,"end_time":1675567199000},{"score":2,"score_max":3,"score_min":1,"flag":1,"level":1,"start_time":1675567080000,"end_time":1675567139000},{"score":4,"score_max":5,"score_min":3,"flag":1,"level":1,"start_time":1675567020000,"end_time":1675567079000},{"score":4,"score_max":7,"score_min":3,"flag":1,"level":1,"start_time":1675566960000,"end_time":1675567019000},{"score":1,"score_max":3,"score_min":1,"flag":1,"level":1,"start_time":1675566900000,"end_time":1675566959000},{"score":0,"score_max":1,"score_min":0,"flag":1,"level":1,"start_time":1675566840000,"end_time":1675566899000},{"score":0,"score_max":0,"score_min":0,"flag":1,"level":1,"start_time":1675566780000,"end_time":1675566839000},{"score":1,"score_max":3,"score_min":0,"flag":1,"level":1,"start_time":1675566720000,"end_time":1675566779000},{"score":1,"score_max":1,"score_min":1,"flag":1,"level":1,"start_time":1675566660000,"end_time":1675566719000},{"score":1,"score_max":1,"score_min":1,"flag":1,"level":1,"start_time":1675566600000,"end_time":1675566659000},{"score":2,"score_max":12,"score_min":1,"flag":1,"level":1,"start_time":1675566540000,"end_time":1675566599000},{"score":17,"score_max":20,"score_min":13,"flag":1,"level":1,"start_time":1675566480000,"end_time":1675566539000},{"score":12,"score_max":17,"score_min":9,"flag":1,"level":1,"start_time":1675566420000,"end_time":1675566479000},{"score":17,"score_max":23,"score_min":10,"flag":1,"level":1,"start_time":1675566360000,"end_time":1675566419000},{"score":4,"score_max":14,"score_min":2,"flag":1,"level":1,"start_time":1675566300000,"end_time":1675566359000},{"score":4,"score_max":7,"score_min":3,"flag":1,"level":1,"start_time":1675566060000,"end_time":1675566119000},{"score":15,"score_max":17,"score_min":13,"flag":1,"level":1,"start_time":1675566000000,"end_time":1675566059000}]