[{"heart_rate":91,"heart_rate_max":96,"heart_rate_min":88,"start_time":1675735140000,"end_time":1675735199000},{"heart_rate":80,"heart_rate_max":89,"heart_rate_min":78,"start_time":1675735080000,"end_time":1675735139000},{"heart_rate":81,"heart_rate_max":86,"heart_rate_min":78,"start_time":1675735020000,"end_time":1675735079000},{"heart_rate":86,"heart_rate_max":99,"heart_rate_min":80,"start_time":1675734960000,"end_time":1675735019000},{"heart_rate":81,"heart_rate_max":84,"heart_rate_min":79,"start_time":1675734900000,"end_time":1675734959000},{"heart_rate":85,"heart_rate_max":90,"heart_rate_min":81,"start_time":1675734840000,"end_time":1675734899000},{"heart_rate":82,"heart_rate_max":86,"heart_rate_min":79,"start_time":1675734780000,"end_time":1675734839000},{"heart_rate":83,"heart_rate_max":85,"heart_rate_min":81,"start_time":1675734720000,"end_time":1675734779000},{"heart_rate":82,"heart_rate_max":85,"heart_rate_min":79,"start_time":1675734660000,"end_time":1675734719000},{"heart_rate":84,"heart_rate_max":88,"heart_rate_min":82,"start_time":1675734600000,"end_time":1675734659000},{"heart_rate":80,"heart_rate_max":83,"heart_rate_min":77,"start_time":1675734540000,"end_time":1675734599000},{"heart_rate":83,"heart_rate_max":86,"heart_rate_min":78,"start_time":1675734480000,"end_time":1675734539000},{"heart_rate":88,"heart_rate_max":92,"heart_rate_min":86,"start_time":1675734420000,"end_time":1675734479000},{"heart_rate":86,"heart_rate_max":90,"heart_rate_min":84,"start_time":1675734360000,"end_time":1675734419000},{"heart_rate":87,"heart_rate_max":96,"heart_rate_min":84,"start_time":1675734300000,"end_time":1675734359000},{"heart_rate":85,"heart_rate_max":89,"heart_rate_min":84,"start_time":1675734240000,"end_time":1675734299000},{"heart_rate":88,"heart_rate_max":95,"heart_rate_min":85,"start_time":1675734180000,"end_time":1675734239000},{"heart_rate":85,"heart_rate_max":90,"heart_rate_min":83,"start_time":1675734120000,"end_time":1675734179000},{"heart_rate":83,"heart_rate_max":88,"heart_rate_min":81,"start_time":1675734060000,"end_time":1675734119000},{"heart_rate":85,"heart_rate_max":90,"heart_rate_min":83,"start_time":1675734000000,"end_time":1675734059000},{"heart_rate":84,"heart_rate_max":88,"heart_rate_min":81,"start_time":1675733940000,"end_time":1675733999000},{"heart_rate":83,"heart_rate_max":87,"heart_rate_min":80,"start_time":1675733880000,"end_time":1675733939000},{"heart_rate":85,"heart_rate_max":91,"heart_rate_min":81,"start_time":1675733820000,"end_time":1675733879000},{"heart_rate":69,"heart_rate_max":90,"heart_rate_min":55,"start_time":1675733760000,"end_time":1675733819000},{"heart_rate":86,"heart_rate_max":89,"heart_rate_min":83,"start_time":1675733700000,"end_time":1675733759000},{"heart_rate":85,"heart_rate_max":89,"heart_rate_min":84,"start_time":1675733640000,"end_time":1675733699000},{"heart_rate":87,"heart_rate_max":95,"heart_rate_min":82,"start_time":1675733580000,"end_time":1675733639000},{"heart_rate":92,"heart_rate_max":105,"heart_rate_min":82,"start_time":1675733520000,"end_time":1675733579000},{"heart_rate":101,"heart_rate_max":103,"heart_rate_min":100,"start_time":1675733460000,"end_time":1675733519000},{"heart_rate":100,"heart_rate_max":101,"heart_rate_min":100,"start_time":1675733400000,"end_time":1675733459000},{"heart_rate":92,"heart_rate_max":96,"heart_rate_min":92,"start_time":1675733340000,"end_time":1675733399000},{"heart_rate":97,"heart_rate_max":100,"heart_rate_min":94,"start_time":1675733280000,"end_time":1675733339000},{"heart_rate":95,"heart_rate_max":98,"heart_rate_min":94,"start_time":1675733220000,"end_time":1675733279000},{"heart_rate":95,"heart_rate_max":96,"heart_rate_min":93,"start_time":1675733160000,"end_time":1675733219000},{"heart_rate":95,"heart_rate_max":97,"heart_rate_min":94,"start_time":1675733100000,"end_time":1675733159000},{"heart_rate":91,"heart_rate_max":92,"heart_rate_min":90,"start_time":1675733040000,"end_time":1675733099000},{"heart_rate":92,"heart_rate_max":98,"heart_rate_min":89,"start_time":1675732980000,"end_time":1675733039000},{"heart_rate":101,"heart_rate_max":103,"heart_rate_min":97,"start_time":1675732920000,"end_time":1675732979000},{"heart_rate":82,"heart_rate_max":83,"heart_rate_min":81,"start_time":1675732800000,"end_time":1675732859000},{"heart_rate":88,"heart_rate_max":99,"heart_rate_min":80,"start_time":1675732740000,"end_time":1675732799000},{"heart_rate":89,"heart_rate_max":95,"heart_rate_min":86,"start_time":1675732680000,"end_time":1675732739000},{"heart_rate":84,"heart_rate_max":96,"heart_rate_min":79,"start_time":1675732620000,"end_time":1675732679000},{"heart_rate":83,"heart_rate_max":86,"heart_rate_min":80,"start_time":1675732560000,"end_time":1675732619000},{"heart_rate":84,"heart_rate_max":90,"heart_rate_min":82,"start_time":1675732500000,"end_time":1675732559000},{"heart_rate":82,"heart_rate_max":88,"heart_rate_min":78,"start_time":1675732440000,"end_time":1675732499000},{"heart_rate":80,"heart_rate_max":84,"heart_rate_min":78,"start_time":1675732380000,"end_time":1675732439000},{"heart_rate":85,"heart_rate_max":88,"heart_rate_min":83,"start_time":1675732320000,"end_time":1675732379000},{"heart_rate":82,"heart_rate_max":86,"heart_rate_min":80,"start_time":1675732260000,"end_time":1675732319000},{"heart_rate":83,"heart_rate_max":86,"heart_rate_min":80,"start_time":1675732200000,"end_time":1675732259000},{"heart_rate":84,"heart_rate_max":88,"heart_rate_min":81,"start_time":1675732140000,"end_time":1675732199000},{"heart_rate":86,"heart_rate_max":91,"heart_rate_min":84,"start_time":1675732080000,"end_time":1675732139000},{"heart_rate":86,"heart_rate_max":92,"heart_rate_min":80,"start_time":1675732020000,"end_time":1675732079000},{"heart_rate":81,"heart_rate_max":85,"heart_rate_min":79,"start_time":1675731960000,"end_time":1675732019000},{"heart_rate":86,"heart_rate_max":92,"heart_rate_min":83,"start_time":1675731900000,"end_time":1675731959000},{"heart_rate":87,"heart_rate_max":92,"heart_rate_min":83,"start_time":1675731840000,"end_time":1675731899000},{"heart_rate":85,"heart_rate_max":89,"heart_rate_min":82,"start_time":1675731780000,"end_time":1675731839000},{"heart_rate":83,"heart_rate_max":87,"heart_rate_min":81,"start_time":1675731720000,"end_time":1675731779000},{"heart_rate":87,"heart_rate_max":93,"heart_rate_min":84,"start_time":1675731660000,"end_time":1675731719000},{"heart_rate":82,"heart_rate_max":87,"heart_rate_min":78,"start_time":1675731600000,"end_time":1675731659000}]