[{"heart_rate":101,"heart_rate_max":104,"heart_rate_min":98,"start_time":1674946740000,"end_time":1674946799000},{"heart_rate":105,"heart_rate_max":111,"heart_rate_min":90,"start_time":1674946680000,"end_time":1674946739000},{"heart_rate":104,"heart_rate_max":104,"heart_rate_min":104,"start_time":1674946620000,"end_time":1674946679000},{"heart_rate":103,"heart_rate_max":103,"heart_rate_min":103,"start_time":1674946560000,"end_time":1674946619000},{"heart_rate":105,"heart_rate_max":106,"heart_rate_min":105,"start_time":1674946260000,"end_time":1674946319000},{"heart_rate":102,"heart_rate_max":104,"heart_rate_min":101,"start_time":1674946200000,"end_time":1674946259000},{"heart_rate":101,"heart_rate_max":102,"heart_rate_min":101,"start_time":1674946080000,"end_time":1674946139000},{"heart_rate":99,"heart_rate_max":104,"heart_rate_min":97,"start_time":1674946020000,"end_time":1674946079000},{"heart_rate":98,"heart_rate_max":103,"heart_rate_min":93,"start_time":1674945960000,"end_time":1674946019000},{"heart_rate":99,"heart_rate_max":104,"heart_rate_min":94,"start_time":1674945900000,"end_time":1674945959000},{"heart_rate":95,"heart_rate_max":102,"heart_rate_min":91,"start_time":1674945840000,"end_time":1674945899000},{"heart_rate":98,"heart_rate_max":106,"heart_rate_min":90,"start_time":1674945780000,"end_time":1674945839000},{"heart_rate":90,"heart_rate_max":91,"heart_rate_min":89,"start_time":1674945660000,"end_time":1674945719000},{"heart_rate":91,"heart_rate_max":94,"heart_rate_min":88,"start_time":1674945540000,"end_time":1674945599000},{"heart_rate":90,"heart_rate_max":97,"heart_rate_min":72,"start_time":1674945480000,"end_time":1674945539000},{"heart_rate":65,"heart_rate_max":74,"heart_rate_min":56,"start_time":1674945420000,"end_time":1674945479000},{"heart_rate":93,"heart_rate_max":100,"heart_rate_min":83,"start_time":1674945360000,"end_time":1674945419000},{"heart_rate":99,"heart_rate_max":105,"heart_rate_min":94,"start_time":1674945300000,"end_time":1674945359000},{"heart_rate":91,"heart_rate_max":96,"heart_rate_min":83,"start_time":1674945240000,"end_time":1674945299000},{"heart_rate":76,"heart_rate_max":84,"heart_rate_min":71,"start_time":1674945180000,"end_time":1674945239000},{"heart_rate":86,"heart_rate_max":96,"heart_rate_min":74,"start_time":1674945120000,"end_time":1674945179000},{"heart_rate":97,"heart_rate_max":103,"heart_rate_min":95,"start_time":1674945060000,"end_time":1674945119000},{"heart_rate":96,"heart_rate_max":103,"heart_rate_min":94,"start_time":1674945000000,"end_time":1674945059000},{"heart_rate":96,"heart_rate_max":99,"heart_rate_min":94,"start_time":1674944940000,"end_time":1674944999000},{"heart_rate":87,"heart_rate_max":89,"heart_rate_min":87,"start_time":1674944880000,"end_time":1674944939000},{"heart_rate":89,"heart_rate_max":93,"heart_rate_min":86,"start_time":1674944820000,"end_time":1674944879000},{"heart_rate":93,"heart_rate_max":98,"heart_rate_min":91,"start_time":1674944760000,"end_time":1674944819000},{"heart_rate":95,"heart_rate_max":98,"heart_rate_min":93,"start_time":1674944700000,"end_time":1674944759000},{"heart_rate":95,"heart_rate_max":100,"heart_rate_min":91,"start_time":1674944640000,"end_time":1674944699000},{"heart_rate":95,"heart_rate_max":99,"heart_rate_min":92,"start_time":1674944580000,"end_time":1674944639000},{"heart_rate":93,"heart_rate_max":100,"heart_rate_min":89,"start_time":1674944520000,"end_time":1674944579000},{"heart_rate":95,"heart_rate_max":100,"heart_rate_min":91,"start_time":1674944460000,"end_time":1674944519000},{"heart_rate":95,"heart_rate_max":99,"heart_rate_min":89,"start_time":1674944400000,"end_time":1674944459000},{"heart_rate":96,"heart_rate_max":100,"heart_rate_min":93,"start_time":1674944340000,"end_time":1674944399000},{"heart_rate":95,"heart_rate_max":97,"heart_rate_min":94,"start_time":1674944280000,"end_time":1674944339000},{"heart_rate":96,"heart_rate_max":105,"heart_rate_min":94,"start_time":1674944220000,"end_time":1674944279000},{"heart_rate":103,"heart_rate_max":109,"heart_rate_min":99,"start_time":1674944160000,"end_time":1674944219000},{"heart_rate":101,"heart_rate_max":105,"heart_rate_min":99,"start_time":1674944100000,"end_time":1674944159000},{"heart_rate":99,"heart_rate_max":103,"heart_rate_min":98,"start_time":1674944040000,"end_time":1674944099000},{"heart_rate":99,"heart_rate_max":104,"heart_rate_min":97,"start_time":1674943980000,"end_time":1674944039000},{"heart_rate":103,"heart_rate_max":109,"heart_rate_min":99,"start_time":1674943920000,"end_time":1674943979000},{"heart_rate":99,"heart_rate_max":112,"heart_rate_min":96,"start_time":1674943860000,"end_time":1674943919000},{"heart_rate":113,"heart_rate_max":113,"heart_rate_min":97,"start_time":1674943800000,"end_time":1674943859000},{"heart_rate":97,"heart_rate_max":100,"heart_rate_min":94,"start_time":1674943740000,"end_time":1674943799000},{"heart_rate":97,"heart_rate_max":100,"heart_rate_min":95,"start_time":1674943680000,"end_time":1674943739000},{"heart_rate":96,"heart_rate_max":99,"heart_rate_min":93,"start_time":1674943620000,"end_time":1674943679000},{"heart_rate":94,"heart_rate_max":97,"heart_rate_min":91,"start_time":1674943560000,"end_time":1674943619000},{"heart_rate":95,"heart_rate_max":98,"heart_rate_min":94,"start_time":1674943500000,"end_time":1674943559000},{"heart_rate":97,"heart_rate_max":99,"heart_rate_min":95,"start_time":1674943440000,"end_time":1674943499000},{"heart_rate":98,"heart_rate_max":101,"heart_rate_min":97,"start_time":1674943380000,"end_time":1674943439000},{"heart_rate":99,"heart_rate_max":102,"heart_rate_min":97,"start_time":1674943320000,"end_time":1674943379000},{"heart_rate":99,"heart_rate_max":103,"heart_rate_min":97,"start_time":1674943260000,"end_time":1674943319000},{"heart_rate":99,"heart_rate_max":106,"heart_rate_min":96,"start_time":1674943200000,"end_time":1674943259000}]